__main__.py
songs.py
test_songs.py
database_songs/MockSongDatabaseHandler.py
database_songs/SongDatabaseHandler.py
database_songs/__init__.py
display_lyrics/BaseDisplayLyrics.py
display_lyrics/ConsoleDisplayLyrics.py
display_lyrics/Lyrics.py
display_lyrics/__init__.py
display_lyrics/test_console_display_lyrics.py
display_lyrics/test_lyrics.py
fetch_lyrics/FetchLyrics.py
fetch_lyrics/PatchedGenius.py
fetch_lyrics/__init__.py
fetch_lyrics/test_fetch_lyrics.py
translate_lyrics/TranslateLyrics.py
translate_lyrics/__init__.py
translate_lyrics/test_translate_lyrics.py
console_songs-2024.11.3.dist-info/LICENSE
console_songs-2024.11.3.dist-info/METADATA
console_songs-2024.11.3.dist-info/WHEEL
console_songs-2024.11.3.dist-info/entry_points.txt
console_songs-2024.11.3.dist-info/top_level.txt
console_songs-2024.11.3.dist-info/RECORD
