Metadata-Version: 2.1
Name: console-songs
Version: 2024.11.3
Summary: Given a song and artist, fetches lyrics from Genius, translates them to English using Azure AI Translator, and displays original and translated lyrics side-by-side in the console.
Author-email: Patrick Kubiak <epicpatka@gmail.com>
Maintainer-email: Patrick Kubiak <epicpatka@gmail.com>
License: MIT License
Keywords: console,songs,genius-lyrics-api,azure-translator
Classifier: Development Status :: 5 - Production/Stable
Classifier: Programming Language :: Python
Classifier: Environment :: Console
Requires-Python: >=3.11
License-File: LICENSE
Requires-Dist: python-dotenv
Requires-Dist: requests
Requires-Dist: lyricsgenius
Requires-Dist: side-by-side
Requires-Dist: beautifulsoup4
Provides-Extra: cli
Requires-Dist: pytest ; extra == 'cli'
Requires-Dist: pytest-cov ; extra == 'cli'
Requires-Dist: black ; extra == 'cli'
Requires-Dist: build ; extra == 'cli'
Requires-Dist: twine ; extra == 'cli'
